linkedin_api/__init__.py
linkedin_api/client.py
linkedin_api/cookie_repository.py
linkedin_api/linkedin.py
linkedin_api/settings.py
linkedin_api/utils/__init__.py
linkedin_api/utils/helpers.py
linkedin_api-2.2.1.dist-info/LICENSE
linkedin_api-2.2.1.dist-info/METADATA
linkedin_api-2.2.1.dist-info/WHEEL
linkedin_api-2.2.1.dist-info/entry_points.txt
linkedin_api-2.2.1.dist-info/RECORD
