Metadata-Version: 2.1
Name: linkedin-api
Version: 2.2.1
Summary: LinkedIn API for Python
Home-page: https://github.com/tomquirk/linkedin-api
License: MIT
Keywords: linkedin,api,automation,scraper,bot,data,sdk,ai,integration,profiles,network,company
Author: Tom Quirk
Author-email: tom@codalabs.au
Maintainer: Tom Quirk
Maintainer-email: tom@codalabs.au
Requires-Python: >=3.10,<4.0
Classifier: License :: OSI Approved :: MIT License
Classifier: Programming Language :: Python :: 3
Classifier: Programming Language :: Python :: 3.10
Classifier: Programming Language :: Python :: 3.11
Classifier: Programming Language :: Python :: 3.12
Requires-Dist: beautifulsoup4 (>=4.12.3,<5.0.0)
Requires-Dist: lxml (>=5.3.0,<6.0.0)
Requires-Dist: requests (>=2.32.3,<3.0.0)
Project-URL: Documentation, https://linkedin-api.readthedocs.io
Project-URL: Repository, https://github.com/tomquirk/linkedin-api
